{
  "category": {
    "id": 3,
    "name": "Основні страви",
    "short_name": "O",
    "special_instructions": ""
  },
  "menu_items": [
    {
      "description": "стейк з телятини зі смородиновим соусом",
      "large_portion_name": "200/30г.",
      "name": "Стейк з телятини зі смородиновим соусом",
      "price_large": 168,
      "price_small": 168,
      "short_name": "O1",
      "small_portion_name": "200/30."
    },
    {
      "description": "сейк свинний у медово-гірчичному соусі",
      "large_portion_name": "200/30г.",
      "name": "Сейк свинний у медово-гірчичному соусі",
      "price_large": 155,
      "price_small": 155,
      "short_name": "O2",
      "small_portion_name": "200/30."
    },    
    {
      "description": "стейк свинний із ошийка",
      "large_portion_name": "200/50г.",
      "name": "Стейк свинний із ошийка",
      "price_large": 172,
      "price_small": 172,
      "short_name": "O3",
      "small_portion_name": "200/50г."
    },
    {
      "description": "куряче філе, сир, мікс салатів, томат, соус.",
      "large_portion_name": "300г.",
      "name": "Курячий стейк під сиром",
      "price_large": 135,
      "price_small": 135,
      "short_name": "O4",
      "small_portion_name": "300г."
    },  
  {
      "description": "куряче філе, бекон, моцарела,мікс салатів, помідор, морква по-корейськи",
      "large_portion_name": "1400г.",
      "name": "Панська курка",
      "price_large": 165,
      "price_small": 165,
      "short_name": "O5",
      "small_portion_name": "1400г."
    },    
    {
      "description": "відбивна зі свинини ",
      "large_portion_name": "110г.",
      "name": "Відбивна зі свинини",
      "price_large": 65,
      "price_small": 65,
      "short_name": "O6",
      "small_portion_name": "110г."
    },
    {
      "description": "куряче стегно, мікс салатів, овочі",
      "large_portion_name": "200/70/30г.",
      "name": "Соковите куряче стегенце ",
      "price_large": 120,
      "price_small": 120,
      "short_name": "O7",
      "small_portion_name": "200/70/30г."
    },
    {
      "description": "курячі крильця під медово-соєвим соусом",
      "large_portion_name": "300г.",
      "name": "Курячі крильця під медово-соєвим соусом",
      "price_large": 95,
      "price_small": 95,
      "short_name": "O8",
      "small_portion_name": "300."
    },
    {
      "description": "курячі сердечка у вершковуму соусі",
      "large_portion_name": "350г.",
      "name": "Курячі сердечка у вершковуму соусі",
      "price_large": 148,
      "price_small": 75148,
      "short_name": "O9",
      "small_portion_name": "350г."
    },    
    {
      "description": "м`ясо свинини, цибуля, томатний соус",
      "large_portion_name": "300г.",
      "name": "М`ясна пательня",
      "price_large": 165,
      "price_small": 96165,
      "short_name": "O10",
      "small_portion_name": "300г."
    },
    {
      "description": "м`ясо свинини, цибуля, вершки, спеції, соєвий соус",
      "large_portion_name": "350г.",
      "name": "М`ясна пательня на вершках",
      "price_large": 220,
      "price_small": 220,
      "short_name": "O11",
      "small_portion_name": "350г."
    },    
    {
      "description": "філе білої рибки, печериці, вершки, спеції ",
      "large_portion_name": "300г.",
      "name": "Пательня з рибкою під крибним соусом",
      "price_large": 170,
      "price_small": 170,
      "short_name": "O12",
      "small_portion_name": "300г."
    },
    {
      "description": "філе білої рибки, цукіні, морква, цибуля, маслини, лимон ",
      "large_portion_name": "300г.",
      "name": "Рибна пательня з овочами ",
      "price_large": 170,
      "price_small": 170,
      "short_name": "O13",
      "small_portion_name": "300г."
    },  
{
      "description": "морський червоний окунь",
      "large_portion_name": "400/30г.",
      "name": "Морський червоний окунь",
      "price_large": 320,
      "price_small": 320,
      "short_name": "O14",
      "small_portion_name": "400/30г."
    },
    {
      "description": "стейк лосося, соус тартар, лимон",
      "large_portion_name": "за 100г.",
      "name": "Стейк лосося",
      "price_large": 140,
      "price_small": 140,
      "short_name": "O15",
      "small_portion_name": "за 100г."
    },    
    {
      "description": "макрель, яйце, печериці, сир моцарела, лимон ",
      "large_portion_name": "250г.",
      "name": "Макрель під сиром з овочами",
      "price_large": 125,
      "price_small": 125,
      "short_name": "O16",
      "small_portion_name": "250г."
    },
    {
      "description": "макрель, солодка паприка,спаржа, цибуля, лимон",
      "large_portion_name": "150г.",
      "name": "Рулетики DI MARE",
      "price_large": 135,
      "price_small": 135,
      "short_name": "O17",
      "small_portion_name": "150г."
    },
 {
      "description": "курка фрі, печериці фрі, ковбаски грль, мисливські ковбски,картопля фрі, соус шашличний, соус майонезно-часниковий ",
      "large_portion_name": "700/30/30г.",
      "name": "Пивна тарілка",
      "price_large": 260,
      "price_small": 260,
      "short_name": "O18",
      "small_portion_name": "700/30/30г."
    },
    {
      "description": "курячі крильця під-медово-гірчічному соусі,мисливські ковбаски, курячий та свинний шашлик,картопля по-селянські, соус шашличний, соус майонезно-часниковий",
      "large_portion_name": "950/30/30г.",
      "name": "М`ясна тарілка",
      "price_large": 310,
      "price_small": 310,
      "short_name": "O19",
      "small_portion_name": "950/30/30г."
    }        
  ]    
  ]
}
